perm_test_punck-0.3.0.dist-info/METADATA
perm_test_punck-0.3.0.dist-info/WHEEL
perm_test_punck-0.3.0.dist-info/licenses/LICENSE
perm_test.libs/libgcc_s-b5472b99.so.1
perm_test/__init__.py
perm_test/perm_test.cpython-313-i386-linux-musl.so
perm_test_punck-0.3.0.dist-info/RECORD
