Metadata-Version: 2.4
Name: perm_test_punck
Version: 0.3.0
Classifier: Programming Language :: Rust
Classifier: Programming Language :: Python :: Implementation :: CPython
Classifier: Programming Language :: Python :: Implementation :: PyPy
License-File: LICENSE
Summary: A rust implementation for fast permutation testing
Author-email: Puck van Gijzen <puckvangijzen@proton.me>
License: MIT
Requires-Python: >=3.8
Project-URL: Homepage, https://gitlab.com/punck/perm_test
Project-URL: Issues, https://gitlab.com/punck/perm_test/issues
